dwlver/__init__.py
dwlver/cli.py
dwlver/dwlver.py
dwlver/ver.py
dwlver-0.2.0.dist-info/DESCRIPTION.rst
dwlver-0.2.0.dist-info/entry_points.txt
dwlver-0.2.0.dist-info/METADATA
dwlver-0.2.0.dist-info/metadata.json
dwlver-0.2.0.dist-info/RECORD
dwlver-0.2.0.dist-info/top_level.txt
dwlver-0.2.0.dist-info/WHEEL
