Metadata-Version: 2.0
Name: dwlver
Version: 0.2.0
Summary: version testing
Home-page: https://github.com/digwanderlust/dwlver
Author: Matt Olsen
Author-email: digwanderlust@gmail.com
License: BSD license
Keywords: dwlver
Platform: UNKNOWN
Classifier: Development Status :: 2 - Pre-Alpha
Classifier: Intended Audience :: Developers
Classifier: Natural Language :: English
Classifier: Programming Language :: Python :: 2
Classifier: Programming Language :: Python :: 2.6
Classifier: Programming Language :: Python :: 2.7
Classifier: Programming Language :: Python :: 3
Classifier: Programming Language :: Python :: 3.3
Classifier: Programming Language :: Python :: 3.4
Classifier: Programming Language :: Python :: 3.5
Requires-Dist: Click (>=6.0)
